[1,["a6x2lioa1JDquemDiAHsUm","29ynrFvq5PxYiOOFlKDLZ7@6c48a"],["node","root","data","_skeletonData"],[["cc.Prefab",["_name"],2],["cc.Node",["_name","_layer","_components","_prefab","_lpos","_lscale"],1,9,4,5,5],["sp.Skeleton",["defaultSkin","defaultAnimation","_premultipliedAlpha","_preCacheMode","node","__prefab","_skeletonData"],-1,1,4,6],["cc.CompPrefabInfo",["fileId"],2],["cc.BoxCollider2D",["_enabled","node","__prefab","_size"],2,1,4,5],["53d87LHChNIvIhwlCOIIRKB",["node","__prefab"],3,1,4],["cc.UIOpacity",["node","__prefab"],3,1,4],["cc.UITransform",["node","__prefab","_contentSize"],3,1,4,5],["cc.PrefabInfo",["fileId","instance","targetOverrides","nestedPrefabInstanceRoots","root","asset"],-1,1,1],["sp.SkeletonData",["_name","_atlasText","textureNames","_skeletonJson","textures"],-1,3]],[[3,0,2],[0,0,2],[1,0,1,2,3,4,5,3],[2,0,1,2,3,4,5,6,5],[4,0,1,2,3,2],[5,0,1,1],[6,0,1,1],[7,0,1,2,1],[8,0,1,2,3,4,5,5],[9,0,1,2,3,4,5]],[[[[1,"ShenWei"],[2,"ShenWei",2,[[3,"default","effect",false,0,-2,[0,"e1zI44a39DBKhBHaCC10Oj"],0],[4,false,-3,[0,"fcW+AD2ghCILtzEraNhLyk"],[5,234,223]],[5,-4,[0,"3dDdUzzv1ONKhYjP8+Orr7"]],[6,-5,[0,"e3mTIrGC9LApQoiylharJk"]],[7,-6,[0,"c7XyBy6QpNfpI0I1Kb4DY/"],[5,234,223]]],[8,"6fpPsOWMJNmY1nhd/PyU0D",null,null,null,-1,0],[1,0,58,0],[1,1.3,1.3,1]]],0,[0,1,1,0,0,1,0,0,1,0,0,1,0,0,1,0,0,1,0,2,1,6],[0],[3],[0]],[[[9,"ShenWei","\r\nShenWei.png\r\nsize: 2048,2048\r\nformat: RGBA8888\r\nfilter: Linear,Linear\r\nrepeat: none\r\nlibrary/1\r\n  rotate: true\r\n  xy: 1204, 1561\r\n  size: 234, 223\r\n  orig: 234, 223\r\n  offset: 0, 0\r\n  index: -1\r\nlibrary/10\r\n  rotate: false\r\n  xy: 2, 4\r\n  size: 327, 306\r\n  orig: 327, 306\r\n  offset: 0, 0\r\n  index: -1\r\nlibrary/11\r\n  rotate: false\r\n  xy: 684, 346\r\n  size: 343, 319\r\n  orig: 343, 319\r\n  offset: 0, 0\r\n  index: -1\r\nlibrary/12\r\n  rotate: true\r\n  xy: 349, 1700\r\n  size: 345, 342\r\n  orig: 345, 342\r\n  offset: 0, 0\r\n  index: -1\r\nlibrary/13\r\n  rotate: true\r\n  xy: 2, 1006\r\n  size: 345, 344\r\n  orig: 345, 344\r\n  offset: 0, 0\r\n  index: -1\r\nlibrary/14\r\n  rotate: false\r\n  xy: 348, 1006\r\n  size: 343, 345\r\n  orig: 343, 345\r\n  offset: 0, 0\r\n  index: -1\r\nlibrary/15\r\n  rotate: false\r\n  xy: 348, 667\r\n  size: 335, 337\r\n  orig: 335, 337\r\n  offset: 0, 0\r\n  index: -1\r\nlibrary/16\r\n  rotate: true\r\n  xy: 591, 2\r\n  size: 327, 335\r\n  orig: 327, 335\r\n  offset: 0, 0\r\n  index: -1\r\nlibrary/17\r\n  rotate: false\r\n  xy: 928, 17\r\n  size: 327, 327\r\n  orig: 327, 327\r\n  offset: 0, 0\r\n  index: -1\r\nlibrary/18\r\n  rotate: false\r\n  xy: 693, 1708\r\n  size: 337, 337\r\n  orig: 337, 337\r\n  offset: 0, 0\r\n  index: -1\r\nlibrary/19\r\n  rotate: false\r\n  xy: 349, 1355\r\n  size: 343, 343\r\n  orig: 343, 343\r\n  offset: 0, 0\r\n  index: -1\r\nlibrary/2\r\n  rotate: true\r\n  xy: 1032, 1797\r\n  size: 248, 242\r\n  orig: 248, 242\r\n  offset: 0, 0\r\n  index: -1\r\nlibrary/20\r\n  rotate: true\r\n  xy: 2, 659\r\n  size: 345, 344\r\n  orig: 345, 344\r\n  offset: 0, 0\r\n  index: -1\r\nlibrary/21\r\n  rotate: false\r\n  xy: 2, 1700\r\n  size: 345, 345\r\n  orig: 345, 345\r\n  offset: 0, 0\r\n  index: -1\r\nlibrary/22\r\n  rotate: false\r\n  xy: 2, 1353\r\n  size: 345, 345\r\n  orig: 345, 345\r\n  offset: 0, 0\r\n  index: -1\r\nlibrary/23\r\n  rotate: false\r\n  xy: 2, 312\r\n  size: 344, 345\r\n  orig: 344, 345\r\n  offset: 0, 0\r\n  index: -1\r\nlibrary/24\r\n  rotate: false\r\n  xy: 348, 331\r\n  size: 334, 334\r\n  orig: 334, 334\r\n  offset: 0, 0\r\n  index: -1\r\nlibrary/25\r\n  rotate: false\r\n  xy: 685, 677\r\n  size: 327, 327\r\n  orig: 327, 327\r\n  offset: 0, 0\r\n  index: -1\r\nlibrary/3\r\n  rotate: true\r\n  xy: 694, 1450\r\n  size: 256, 253\r\n  orig: 256, 253\r\n  offset: 0, 0\r\n  index: -1\r\nlibrary/4\r\n  rotate: true\r\n  xy: 331, 46\r\n  size: 264, 258\r\n  orig: 264, 258\r\n  offset: 0, 0\r\n  index: -1\r\nlibrary/5\r\n  rotate: true\r\n  xy: 1197, 1214\r\n  size: 234, 225\r\n  orig: 234, 225\r\n  offset: 0, 0\r\n  index: -1\r\nlibrary/6\r\n  rotate: true\r\n  xy: 953, 1200\r\n  size: 248, 242\r\n  orig: 248, 242\r\n  offset: 0, 0\r\n  index: -1\r\nlibrary/7\r\n  rotate: true\r\n  xy: 949, 1450\r\n  size: 256, 253\r\n  orig: 256, 253\r\n  offset: 0, 0\r\n  index: -1\r\nlibrary/8\r\n  rotate: true\r\n  xy: 693, 1089\r\n  size: 264, 258\r\n  orig: 264, 258\r\n  offset: 0, 0\r\n  index: -1\r\nlibrary/9\r\n  rotate: false\r\n  xy: 1014, 965\r\n  size: 232, 233\r\n  orig: 232, 233\r\n  offset: 0, 0\r\n  index: -1\r\n",["ShenWei.png"],{"skeleton":{"hash":"5ExIfKcZrsM3Vok3TJs3pSVGqUM","spine":"3.8.75","x":57,"y":-108,"width":234,"height":223,"images":"","audio":""},"bones":[{"name":"root","x":174,"y":3.5},{"name":"bone","parent":"root"}],"slots":[{"name":"slot","bone":"bone","attachment":"library/1"}],"skins":[{"name":"default","attachments":{"slot":{"library/1":{"width":234,"height":223},"library/2":{"width":248,"height":242},"library/3":{"width":256,"height":253},"library/4":{"width":264,"height":258},"library/5":{"width":234,"height":225},"library/6":{"width":248,"height":242},"library/7":{"width":256,"height":253},"library/8":{"width":264,"height":258},"library/9":{"width":232,"height":233},"library/10":{"width":327,"height":306},"library/11":{"width":343,"height":319},"library/12":{"width":345,"height":342},"library/13":{"width":345,"height":344},"library/14":{"width":343,"height":345},"library/15":{"width":335,"height":337},"library/16":{"width":327,"height":335},"library/17":{"width":327,"height":327},"library/18":{"width":337,"height":337},"library/19":{"width":343,"height":343},"library/20":{"width":345,"height":344},"library/21":{"width":345,"height":345},"library/22":{"width":345,"height":345},"library/23":{"width":344,"height":345},"library/24":{"width":334,"height":334},"library/25":{"width":327,"height":327}}}}],"events":{"closeBox":{},"openBox":{}},"animations":{"effect":{"slots":{"slot":{"attachment":[{"time":0.0333,"name":"library/2"},{"time":0.0667,"name":"library/3"},{"time":0.1,"name":"library/4"},{"time":0.1333,"name":"library/5"},{"time":0.1667,"name":"library/6"},{"time":0.2,"name":"library/7"},{"time":0.2333,"name":"library/8"},{"time":0.2667,"name":"library/9"},{"time":0.3,"name":"library/10"},{"time":0.3333,"name":"library/11"},{"time":0.3667,"name":"library/12"},{"time":0.4,"name":"library/13"},{"time":0.4333,"name":"library/14"},{"time":0.4667,"name":"library/15"},{"time":0.5,"name":"library/16"},{"time":0.5333,"name":"library/17"},{"time":0.5667,"name":"library/18"},{"time":0.6,"name":"library/19"},{"time":0.6333,"name":"library/20"},{"time":0.6667,"name":"library/21"},{"time":0.7,"name":"library/22"},{"time":0.7333,"name":"library/23"},{"time":0.7667,"name":"library/24"},{"time":0.8,"name":"library/25"}]}},"bones":{"bone":{"translate":[{"x":-180,"y":-4.5,"curve":"stepped"},{"time":0.3,"x":-174.5,"y":1,"curve":"stepped"},{"time":0.3333,"x":-174.5,"y":1.5,"curve":"stepped"},{"time":0.3667,"x":-174.5,"y":1,"curve":"stepped"},{"time":0.4,"x":-174.5,"y":1,"curve":"stepped"},{"time":0.4333,"x":-174.5,"y":0.5,"curve":"stepped"},{"time":0.6,"x":-174.5,"y":0.5,"curve":"stepped"},{"time":0.0333,"x":-175,"y":5,"curve":"stepped"},{"time":0.6333,"x":-174.5,"curve":"stepped"},{"time":0.6667,"x":-174.5,"y":0.5,"curve":"stepped"},{"time":0.7,"x":-174.5,"y":0.5,"curve":"stepped"},{"time":0.7333,"x":-175,"y":0.5,"curve":"stepped"},{"time":0.7667,"x":-178,"y":4,"curve":"stepped"},{"time":0.8,"x":-174.5,"y":0.5,"curve":"stepped"},{"time":0.0667,"x":-176,"y":0.5,"curve":"stepped"},{"time":0.1,"x":-178,"curve":"stepped"},{"time":0.1333,"x":-180,"y":-3.5,"curve":"stepped"},{"time":0.1667,"x":-175,"y":5,"curve":"stepped"},{"time":0.2,"x":-176,"y":0.5,"curve":"stepped"},{"time":0.2333,"x":-178,"curve":"stepped"},{"time":0.2667,"x":-174,"y":0.5}]}},"events":[{"time":0.3667,"name":"openBox"},{"time":0.6667,"name":"closeBox"}]}}},[0]]],0,0,[0],[-1],[1]]]]
